esa_wiki/__init__.py
esa_wiki/cunning_linguistics.py
esa_wiki/generate_indices.py
esa_wiki/matrix_builder.py
esa_wiki/shared.py
esa_wiki/wikicleaner.py
esa_wiki/xml_parse.py
esa_wiki-0.0.1.dist-info/METADATA
esa_wiki-0.0.1.dist-info/WHEEL
esa_wiki-0.0.1.dist-info/top_level.txt
esa_wiki-0.0.1.dist-info/RECORD
