Metadata-Version: 2.1
Name: esa-wiki
Version: 0.0.1
Summary: Explicit Semantic Analysis
Home-page: UNKNOWN
Author: Bjarke Mønsted
License: UNKNOWN
Platform: UNKNOWN
Classifier: Programming Language :: Python :: 3
Classifier: Operating System :: OS Independent
